kinesispipeline/__init__.py
kinesispipeline/pipelines.py
scrapy_kinesispipeline-0.3.9.dist-info/DESCRIPTION.rst
scrapy_kinesispipeline-0.3.9.dist-info/METADATA
scrapy_kinesispipeline-0.3.9.dist-info/RECORD
scrapy_kinesispipeline-0.3.9.dist-info/WHEEL
scrapy_kinesispipeline-0.3.9.dist-info/metadata.json
scrapy_kinesispipeline-0.3.9.dist-info/top_level.txt
