Metadata-Version: 2.0
Name: scrapy-kinesispipeline
Version: 0.3.9
Summary: Scrapy pipeline to store aggregated items into AWS Kinesis
Home-page: https://github.com/fleiheit/scrapy-kinesispipeline
Author: Atabak Hafeez
Author-email: atabakhafeez@hotmail.com
License: MIT
Keywords: scrapy pipeline aws kinesis serverless
Platform: UNKNOWN
Classifier: Development Status :: 4 - Beta
Classifier: License :: OSI Approved :: MIT License
Classifier: Programming Language :: Python :: 3
Classifier: Programming Language :: Python :: 3.4
Classifier: Programming Language :: Python :: 3.5
Classifier: Programming Language :: Python :: 3.6
Classifier: Framework :: Scrapy
Requires-Dist: Scrapy (>=1.1)
Requires-Dist: boto3
Requires-Dist: botocore
